{
  "terms": [
    {
      "id": "000",
      "name": "Humaniora",
      "subterms": [
        {
          "id": "010",
          "name": "Språkvitenskapelige fag",
          "subterms": [
            {
              "id": "011",
              "name": "Allmenn språkvitenskap og fonetikk"
            },
            {
              "id": "012",
              "name": "Anvendt språkvitenskap"
            },
            {
              "id": "013",
              "name": "Tegnspråk"
            },
            {
              "id": "018",
              "name": "Nordiske språk"
            },
            {
              "id": "019",
              "name": "Norrøn filologi"
            },
            {
              "id": "020",
              "name": "Engelsk språk"
            },
            {
              "id": "021",
              "name": "Tysk språk"
            },
            {
              "id": "022",
              "name": "Nederlandsk språk"
            },
            {
              "id": "023",
              "name": "Andre germanske språk"
            },
            {
              "id": "024",
              "name": "Fransk språk"
            },
            {
              "id": "025",
              "name": "Italiensk språk"
            },
            {
              "id": "026",
              "name": "Spansk språk"
            },
            {
              "id": "027",
              "name": "Andre romanske språk"
            },
            {
              "id": "028",
              "name": "Russisk språk"
            },
            {
              "id": "029",
              "name": "Andre slaviske språk"
            },
            {
              "id": "030",
              "name": "Finsk-ugriske språk"
            },
            {
              "id": "031",
              "name": "Samisk språk"
            },
            {
              "id": "032",
              "name": "Klassisk filologi"
            },
            {
              "id": "033",
              "name": "Indoeuropeiske språk"
            },
            {
              "id": "034",
              "name": "Østasiatiske språk"
            },
            {
              "id": "035",
              "name": "Semittiske språk"
            },
            {
              "id": "036",
              "name": "Afrikanske språk"
            },
            {
              "id": "037",
              "name": "Stillehavsspråk"
            },
            {
              "id": "038",
              "name": "Tyrkiske språk"
            },
            {
              "id": "039",
              "name": "Andre språkvitenskapelige fag"
            }
          ]
        },
        {
          "id": "040",
          "name": "Litteraturvitenskapelige fag",
          "subterms": [
            {
              "id": "041",
              "name": "Allmenn litteraturvitenskap"
            },
            {
              "id": "042",
              "name": "Nordisk litteratur"
            },
            {
              "id": "043",
              "name": "Engelsk litteratur"
            },
            {
              "id": "044",
              "name": "Tysk litteratur"
            },
            {
              "id": "045",
              "name": "Annen germansk litteratur"
            },
            {
              "id": "046",
              "name": "Fransk litteratur"
            },
            {
              "id": "047",
              "name": "Italiensk litteratur"
            },
            {
              "id": "048",
              "name": "Spansk litteratur"
            },
            {
              "id": "049",
              "name": "Annen romansk litteratur"
            },
            {
              "id": "050",
              "name": "Russisk litteratur"
            },
            {
              "id": "051",
              "name": "Annen slavisk litteratur"
            },
            {
              "id": "052",
              "name": "Finsk litteratur"
            },
            {
              "id": "053",
              "name": "Samisk litteratur"
            },
            {
              "id": "054",
              "name": "Klassisk litteratur"
            },
            {
              "id": "055",
              "name": "Indoeuropeisk litteratur"
            },
            {
              "id": "056",
              "name": "Østasiatisk litteratur"
            },
            {
              "id": "057",
              "name": "Semittisk litteratur"
            },
            {
              "id": "058",
              "name": "Afrikansk litteratur"
            },
            {
              "id": "059",
              "name": "Andre litteraturvitenskapelige fag"
            }
          ]
        },
        {
          "id": "060",
          "name": "Kulturvitenskap",
          "subterms": [
            {
              "id": "061",
              "name": "Nordisk kulturvitenskap"
            },
            {
              "id": "062",
              "name": "Germansk kulturvitenskap"
            },
            {
              "id": "063",
              "name": "Romansk kulturvitenskap"
            },
            {
              "id": "064",
              "name": "Slavisk kulturvitenskap"
            },
            {
              "id": "065",
              "name": "Klassisk kulturvitenskap"
            },
            {
              "id": "066",
              "name": "Indoeuropeisk kulturvitenskap"
            },
            {
              "id": "067",
              "name": "Østasiatisk kulturvitenskap"
            },
            {
              "id": "068",
              "name": "Angloamerikansk kulturvitenskap"
            },
            {
              "id": "069",
              "name": "Annen kulturvitenskap"
            }
          ]
        },
        {
          "id": "070",
          "name": "Historie",
          "subterms": [
            {
              "id": "071",
              "name": "Politisk historie"
            },
            {
              "id": "072",
              "name": "Sosialhistorie"
            },
            {
              "id": "073",
              "name": "Kvinnehistorie"
            },
            {
              "id": "074",
              "name": "Økonomiskhistorie"
            },
            {
              "id": "075",
              "name": "Kulturhistorie"
            },
            {
              "id": "080",
              "name": "Oldtidenshistorie"
            },
            {
              "id": "081",
              "name": "Middelalderhistorie"
            },
            {
              "id": "082",
              "name": "Nyere tids historie (før1800)"
            },
            {
              "id": "083",
              "name": "Modernehistorie (etter1800)"
            },
            {
              "id": "084",
              "name": "Samtidshistorie (etter1945)"
            },
            {
              "id": "085",
              "name": "Ikke-europeisk/-vestlighistorie"
            },
            {
              "id": "089",
              "name": "Annen historie"
            }
          ]
        },
        {
          "id": "090",
          "name": "Arkeologi",
          "subterms": [
            {
              "id": "091",
              "name": "Nordisk arkeologi"
            },
            {
              "id": "092",
              "name": "Klassisk arkeologi"
            },
            {
              "id": "099",
              "name": "Annen arkeologi"
            }
          ]
        },
        {
          "id": "100",
          "name": "Folkloristikk, etnologi",
          "subterms": [
            {
              "id": "101",
              "name": "Folkloristikk"
            },
            {
              "id": "102",
              "name": "Etnologi"
            }
          ]
        },
        {
          "id": "110",
          "name": "Musikkvitenskap",
          "subterms": [
            {
              "id": "111",
              "name": "Musikkhistorie"
            },
            {
              "id": "112",
              "name": "Musikkteori"
            },
            {
              "id": "113",
              "name": "Musikkterapi"
            },
            {
              "id": "114",
              "name": "Musikkpedagogikk"
            },
            {
              "id": "119",
              "name": "Annen musikkvitenskap"
            }
          ]
        },
        {
          "id": "120",
          "name": "Kunsthistorie",
          "subterms": [
            {
              "id": "121",
              "name": "Skulptur"
            },
            {
              "id": "122",
              "name": "Maleri, tegning, grafikk"
            },
            {
              "id": "123",
              "name": "Folkekunst, kunsthåndverk"
            },
            {
              "id": "124",
              "name": "Konservering og restaurering"
            },
            {
              "id": "125",
              "name": "Antikkens kunsthistorie"
            },
            {
              "id": "126",
              "name": "Middelalderkunsthistorie"
            },
            {
              "id": "127",
              "name": "Fra renessanse-t.o.m.barokk"
            },
            {
              "id": "128",
              "name": "Nyere tids kunsthistorie"
            },
            {
              "id": "129",
              "name": "Moderne kunsthistorie"
            },
            {
              "id": "130",
              "name": "Ikke-europeisk kunsthistorie"
            },
            {
              "id": "139",
              "name": "Annen kunsthistorie"
            }
          ]
        },
        {
          "id": "140",
          "name": "Arkitektur og design",
          "subterms": [
            {
              "id": "141",
              "name": "Arkitektur- og designhistorie"
            },
            {
              "id": "142",
              "name": "Arkitektur- og designteori"
            },
            {
              "id": "143",
              "name": "Prosjekterings- og formgivningsmetodikk"
            },
            {
              "id": "147",
              "name": "Landskapsarkitektur"
            }
          ]
        },
        {
          "id": "150",
          "name": "Teologi og religionsvitenskap",
          "subterms": [
            {
              "id": "151",
              "name": "Teologi"
            },
            {
              "id": "152",
              "name": "Kristendomskunnskap"
            },
            {
              "id": "153",
              "name": "Religionsvitenskap, religionshistorie"
            }
          ]
        },
        {
          "id": "160",
          "name": "Filosofiske fag",
          "subterms": [
            {
              "id": "161",
              "name": "Filosofi"
            },
            {
              "id": "162",
              "name": "Idéhistorie"
            },
            {
              "id": "163",
              "name": "Logikk"
            },
            {
              "id": "164",
              "name": "Etikk"
            },
            {
              "id": "169",
              "name": "Andre filosofiske fag"
            }
          ]
        },
        {
          "id": "170",
          "name": "Film- og teatervitenskap",
          "subterms": [
            {
              "id": "171",
              "name": "Filmvitenskap"
            },
            {
              "id": "172",
              "name": "Teatervitenskap"
            }
          ]
        }
      ]
    },
    {
      "id": "200",
      "name": "Samfunnsvitenskap",
      "subterms": [
        {
          "id": "210",
          "name": "Økonomi",
          "subterms": [
            {
              "id": "212",
              "name": "Samfunnsøkonomi"
            },
            {
              "id": "213",
              "name": "Bedriftsøkonomi"
            },
            {
              "id": "214",
              "name": "Økonometri"
            }
          ]
        },
        {
          "id": "220",
          "name": "Sosiologi"
        },
        {
          "id": "230",
          "name": "Urbanisme og fysiskplanlegging",
          "subterms": [
            {
              "id": "231",
              "name": "Planleggingshistorie, -teoriog-metodikk"
            },
            {
              "id": "234",
              "name": "Bebyggelses- og reguleringsplanlegging"
            },
            {
              "id": "236",
              "name": "Landskapsplanlegging"
            },
            {
              "id": "237",
              "name": "Urbanisme"
            },
            {
              "id": "238",
              "name": "Romlig, territoriell planlegging"
            }
          ]
        },
        {
          "id": "240",
          "name": "Statsvitenskap og organisasjonsteori",
          "subterms": [
            {
              "id": "241",
              "name": "Sammenlignende politikk"
            },
            {
              "id": "242",
              "name": "Offentlig og privatadministrasjon"
            },
            {
              "id": "243",
              "name": "Internasjonal politikk"
            }
          ]
        },
        {
          "id": "250",
          "name": "Sosialantropologi"
        },
        {
          "id": "260",
          "name": "Psykologi",
          "subterms": [
            {
              "id": "261",
              "name": "Biologisk psykologi"
            },
            {
              "id": "262",
              "name": "Klinisk psykologi"
            },
            {
              "id": "263",
              "name": "Sosial- og arbeidspsykologi"
            },
            {
              "id": "264",
              "name": "Personlighetspsykologi"
            },
            {
              "id": "265",
              "name": "Utviklingspsykologi"
            },
            {
              "id": "267",
              "name": "Kognitivpsykologi"
            },
            {
              "id": "268",
              "name": "Organisasjonspsykologi"
            },
            {
              "id": "279",
              "name": "Andre psykologiskefag"
            }
          ]
        },
        {
          "id": "280",
          "name": "Pedagogiskefag",
          "subterms": [
            {
              "id": "281",
              "name": "Allmennpedagogikk"
            },
            {
              "id": "282",
              "name": "Spesialpedagogikk"
            },
            {
              "id": "283",
              "name": "Fagdidaktikk"
            },
            {
              "id": "289",
              "name": "Andrepedagogiskefag"
            }
          ]
        },
        {
          "id": "290",
          "name": "Samfunnsgeografi"
        },
        {
          "id": "300",
          "name": "Demografi"
        },
        {
          "id": "310",
          "name": "Medievitenskap og journalistikk"
        },
        {
          "id": "320",
          "name": "Biblioteks- og informasjonsvitenskap",
          "subterms": [
            {
              "id": "321",
              "name": "Informasjons- og kommunikasjonssystemer"
            },
            {
              "id": "322",
              "name": "Informasjonspolitikk"
            },
            {
              "id": "323",
              "name": "Kunnskapsgjenfinning og organisering"
            },
            {
              "id": "324",
              "name": "Bibliometri"
            },
            {
              "id": "325",
              "name": "Dokumentasjonsvitenskap"
            },
            {
              "id": "326",
              "name": "Arkivistikk"
            }
          ]
        },
        {
          "id": "330",
          "name": "Samfunnsvitenskapelige idrettsfag",
          "subterms": [
            {
              "id": "331",
              "name": "Integreringsfag"
            },
            {
              "id": "332",
              "name": "Aktivitetslære"
            },
            {
              "id": "333",
              "name": "Idrettspedagogikk og -psykologi"
            },
            {
              "id": "339",
              "name": "Andre idrettsfag"
            }
          ]
        },
        {
          "id": "340",
          "name": "Rettsvitenskap",
          "subterms": [
            {
              "id": "341",
              "name": "Allmennrettsvitenskap"
            },
            {
              "id": "342",
              "name": "Privatrett"
            },
            {
              "id": "343",
              "name": "Offentligrett"
            },
            {
              "id": "344",
              "name": "Folkerett"
            },
            {
              "id": "346",
              "name": "Rettsinformatikk"
            },
            {
              "id": "347",
              "name": "Miljørett"
            },
            {
              "id": "348",
              "name": "Fiskerirett"
            },
            {
              "id": "349",
              "name": "Andre rettsvitenskapeligefag"
            }
          ]
        },
        {
          "id": "350",
          "name": "Kriminologi"
        },
        {
          "id": "360",
          "name": "Sosialt arbeid"
        },
        {
          "id": "370",
          "name": "Kvinne- og kjønnsstudier"
        }
      ]
    },
    {
      "id": "400",
      "name": "Matematikk og Naturvitenskap",
      "subterms": [
        {
          "id": "410",
          "name": "Matematikk",
          "subterms": [
            {
              "id": "411",
              "name": "Analyse"
            },
            {
              "id": "412",
              "name": "Statistikk"
            },
            {
              "id": "413",
              "name": "Anvendt matematikk"
            },
            {
              "id": "414",
              "name": "Algebra/algebraiskanalyse"
            },
            {
              "id": "415",
              "name": "Topologi/geometri"
            },
            {
              "id": "416",
              "name": "Logikk"
            },
            {
              "id": "417",
              "name": "Forsikringsmatematikk og risikoanalyse"
            }
          ]
        },
        {
          "id": "420",
          "name": "Informasjons- og kommunikasjonsvitenskap",
          "subterms": [
            {
              "id": "421",
              "name": "Teoretisk databehandling, programmeringsspråk og -teori"
            },
            {
              "id": "422",
              "name": "Algoritmerogberegnbarhetsteori"
            },
            {
              "id": "423",
              "name": "Kommunikasjonogdistribuertesystemer"
            },
            {
              "id": "424",
              "name": "Sikkerhetogsårbarhet"
            },
            {
              "id": "425",
              "name": "Kunnskapsbasertesystemer"
            },
            {
              "id": "426",
              "name": "Systemutviklingog–arbeid"
            },
            {
              "id": "427",
              "name": "Matematisk modellering og numeriske metoder"
            },
            {
              "id": "428",
              "name": "Databaser og multimediasystemer"
            },
            {
              "id": "429",
              "name": "Simulering, visualisering, signalbehandling, bildeanalyse"
            }
          ]
        },
        {
          "id": "430",
          "name": "Fysikk",
          "subterms": [
            {
              "id": "431",
              "name": "Kjerne- og elementærpartikkelfysikk"
            },
            {
              "id": "433",
              "name": "Atomfysikk, molekylfysikk"
            },
            {
              "id": "434",
              "name": "Elektromagnetisme, akustikk, optikk"
            },
            {
              "id": "435",
              "name": "Elektronikk"
            },
            {
              "id": "436",
              "name": "Kondenserte fasers fysikk"
            },
            {
              "id": "437",
              "name": "Rom- og plasmafysikk"
            },
            {
              "id": "438",
              "name": "Astrofysikk, astronomi"
            }
          ]
        },
        {
          "id": "440",
          "name": "Kjemi",
          "subterms": [
            {
              "id": "441",
              "name": "Organisk kjemi"
            },
            {
              "id": "442",
              "name": "Uorganisk kjemi"
            },
            {
              "id": "443",
              "name": "Fysikalsk kjemi"
            },
            {
              "id": "444",
              "name": "Teoretisk kjemi, kvantekjemi"
            },
            {
              "id": "445",
              "name": "Analytisk kjemi"
            },
            {
              "id": "446",
              "name": "Miljøkjemi, naturmiljøkjemi"
            },
            {
              "id": "447",
              "name": "Kjernekjemi"
            },
            {
              "id": "448",
              "name": "Legemiddelkjemi"
            }
          ]
        },
        {
          "id": "450",
          "name": "Geofag",
          "subterms": [
            {
              "id": "451",
              "name": "Faste jords fysikk"
            },
            {
              "id": "452",
              "name": "Oseanografi"
            },
            {
              "id": "453",
              "name": "Meteorologi"
            },
            {
              "id": "454",
              "name": "Hydrologi"
            },
            {
              "id": "455",
              "name": "Naturgeografi"
            },
            {
              "id": "456",
              "name": "Sedimentologi"
            },
            {
              "id": "461",
              "name": "Stratigrafi og paleontologi"
            },
            {
              "id": "462",
              "name": "Mineralogi, petrologi, geokjemi"
            },
            {
              "id": "463",
              "name": "Tektonikk"
            },
            {
              "id": "464",
              "name": "Petroleumsgeologi og -geofysikk"
            },
            {
              "id": "465",
              "name": "Kvartærgeologi, glasiologi"
            },
            {
              "id": "466",
              "name": "Maringeologi"
            },
            {
              "id": "467",
              "name": "Hydrogeologi"
            },
            {
              "id": "468",
              "name": "Geometrikk"
            },
            {
              "id": "469",
              "name": "Andregeofag"
            }
          ]
        },
        {
          "id": "470",
          "name": "Basalebiofag",
          "subterms": [
            {
              "id": "471",
              "name": "Cellebiologi"
            },
            {
              "id": "472",
              "name": "Generellmikrobiologi"
            },
            {
              "id": "473",
              "name": "Molekylærbiologi"
            },
            {
              "id": "474",
              "name": "Genetikkoggenomikk"
            },
            {
              "id": "475",
              "name": "Bioinformatikk"
            },
            {
              "id": "476",
              "name": "Biokjemi"
            },
            {
              "id": "477",
              "name": "Biofysikk"
            },
            {
              "id": "478",
              "name": "Generellimmunologi"
            }
          ]
        },
        {
          "id": "480",
          "name": "Zoologiskeogbotaniskefag",
          "subterms": [
            {
              "id": "481",
              "name": "Zoologiskanatomi"
            },
            {
              "id": "482",
              "name": "Embryologi"
            },
            {
              "id": "483",
              "name": "Zoofysiologi og komparativfysiologi"
            },
            {
              "id": "484",
              "name": "Parasittologi"
            },
            {
              "id": "485",
              "name": "Etologi"
            },
            {
              "id": "486",
              "name": "Zoogeografi"
            },
            {
              "id": "487",
              "name": "Systematisk zoologi"
            },
            {
              "id": "488",
              "name": "Økologi"
            },
            {
              "id": "489",
              "name": "Økotoksikologi"
            },
            {
              "id": "491",
              "name": "Planteanatomi"
            },
            {
              "id": "492",
              "name": "Plantefysiologi"
            },
            {
              "id": "493",
              "name": "Systematiskbotanikk"
            },
            {
              "id": "495",
              "name": "Vegetasjonshistorie"
            },
            {
              "id": "496",
              "name": "Plantegeografi"
            },
            {
              "id": "497",
              "name": "Marinbiologi"
            },
            {
              "id": "498",
              "name": "Limnologi"
            }
          ]
        }
      ]
    },
    {
      "id": "500",
      "name": "Teknologi",
      "subterms": [
        {
          "id": "510",
          "name": "Berg- og petroleumsfag",
          "subterms": [
            {
              "id": "511",
              "name": "Bergteknologi"
            },
            {
              "id": "512",
              "name": "Petroleumsteknologi"
            },
            {
              "id": "513",
              "name": "Geoteknikk"
            },
            {
              "id": "519",
              "name": "Andreberg- og petroleumsfagg"
            }
          ]
        },
        {
          "id": "520",
          "name": "Materialteknologi",
          "subterms": [
            {
              "id": "521",
              "name": "Metallurgi"
            },
            {
              "id": "522",
              "name": "Funksjonelle materialer"
            },
            {
              "id": "523",
              "name": "Plast- og komposittmaterialer"
            },
            {
              "id": "525",
              "name": "Bygningsmaterialer"
            },
            {
              "id": "529",
              "name": "Annen materialteknologi"
            }
          ]
        },
        {
          "id": "530",
          "name": "Bygningsfag",
          "subterms": [
            {
              "id": "531",
              "name": "Arkitektur og bygningsteknologi"
            },
            {
              "id": "532",
              "name": "Bygg-, anleggs- og transportteknologi"
            },
            {
              "id": "533",
              "name": "Konstruksjonsteknologi"
            },
            {
              "id": "534",
              "name": "Kartogoppmåling"
            },
            {
              "id": "535",
              "name": "Fysisk planlegging"
            },
            {
              "id": "537",
              "name": "Geoteknologi"
            },
            {
              "id": "538",
              "name": "Hydroteknologi"
            }
          ]
        },
        {
          "id": "540",
          "name": "Elektrotekniske fag",
          "subterms": [
            {
              "id": "541",
              "name": "Elektronikk"
            },
            {
              "id": "542",
              "name": "Elkraft"
            },
            {
              "id": "549",
              "name": "Andre elektrotekniskefag"
            }
          ]
        },
        {
          "id": "550",
          "name": "Informasjons- og kommunikasjonsteknologi",
          "subterms": [
            {
              "id": "551",
              "name": "Datateknologi"
            },
            {
              "id": "552",
              "name": "Telekommunikasjon"
            },
            {
              "id": "553",
              "name": "Tekniskkybernetikk"
            },
            {
              "id": "555",
              "name": "Geografiske informasjonssystemer"
            },
            {
              "id": "559",
              "name": "Annen informasjonsteknologi"
            }
          ]
        },
        {
          "id": "560",
          "name": "Kjemisk teknologi",
          "subterms": [
            {
              "id": "561",
              "name": "Elektrokjemi"
            },
            {
              "id": "562",
              "name": "Kjemiskprosessteknologi"
            },
            {
              "id": "563",
              "name": "Kjemiteknikk"
            },
            {
              "id": "568",
              "name": "Farmasøytisk formulering og teknologi"
            },
            {
              "id": "569",
              "name": "Annen kjemiskteknologi"
            }
          ]
        },
        {
          "id": "570",
          "name": "Maskinfag",
          "subterms": [
            {
              "id": "571",
              "name": "Maskinkonstruksjon og materialteknologi"
            },
            {
              "id": "572",
              "name": "Produksjon og driftsteknologi"
            },
            {
              "id": "573",
              "name": "Maskintekniskenergi- og miljøteknologi"
            },
            {
              "id": "574",
              "name": "Mekaniske og strømningstekniske fag"
            },
            {
              "id": "579",
              "name": "Andre maskinfag"
            }
          ]
        },
        {
          "id": "580",
          "name": "Marinteknologi",
          "subterms": [
            {
              "id": "581",
              "name": "Offshoreteknologi"
            },
            {
              "id": "582",
              "name": "Skipsteknologi"
            },
            {
              "id": "589",
              "name": "Annen marinteknologi"
            }
          ]
        },
        {
          "id": "590",
          "name": "Bioteknologi"
        },
        {
          "id": "600",
          "name": "Næringsmiddelteknologi"
        },
        {
          "id": "610",
          "name": "Miljøteknologi"
        },
        {
          "id": "620",
          "name": "Medisinsk teknologi"
        },
        {
          "id": "630",
          "name": "Nanoteknologi"
        },
        {
          "id": "640",
          "name": "Industri- og produktdesign"
        }
      ]
    },
    {
      "id": "700",
      "name": "Medisinske Fag",
      "subterms": [
        {
          "id": "710",
          "name": "Basalemedisinske, odontologiske og veterinærmedisinske fag",
          "subterms": [
            {
              "id": "711",
              "name": "Medisinsk molekylærbiologi"
            },
            {
              "id": "714",
              "name": "Medisinsk genetikk"
            },
            {
              "id": "715",
              "name": "Medisinsk mikrobiologi"
            },
            {
              "id": "716",
              "name": "Medisinsk immunologi"
            },
            {
              "id": "717",
              "name": "Anatomi, fysiskantropologi"
            },
            {
              "id": "718",
              "name": "Human og veterinærmedisinsk fysiologi"
            },
            {
              "id": "719",
              "name": "Generellpatologi, patologiskanatomi"
            },
            {
              "id": "720",
              "name": "Rettsmedisin, rettsodontologi"
            },
            {
              "id": "721",
              "name": "Patofysiologi"
            },
            {
              "id": "725",
              "name": "Kliniskkjemi"
            },
            {
              "id": "726",
              "name": "Medisinskbiokjemi"
            },
            {
              "id": "728",
              "name": "Farmakologi"
            },
            {
              "id": "730",
              "name": "Toksikologi"
            },
            {
              "id": "736",
              "name": "Biofarmasi"
            },
            {
              "id": "738",
              "name": "Farmakognosi"
            },
            {
              "id": "739",
              "name": "Kliniskfarmakologi"
            }
          ]
        },
        {
          "id": "750",
          "name": "Klinisk medisinske fag",
          "subterms": [
            {
              "id": "751",
              "name": "Allmennmedisin"
            },
            {
              "id": "752",
              "name": "Nevrologi"
            },
            {
              "id": "753",
              "name": "Dermatologi og venerologi"
            },
            {
              "id": "754",
              "name": "Oftalmologi"
            },
            {
              "id": "755",
              "name": "Otorhinolaryngologi"
            },
            {
              "id": "756",
              "name": "Gynekologi og obstetrikk"
            },
            {
              "id": "757",
              "name": "Psykiatri, barnepsykiatri"
            },
            {
              "id": "758",
              "name": "Rettspsykiatri"
            },
            {
              "id": "759",
              "name": "Reumatologi"
            },
            {
              "id": "760",
              "name": "Pediatri"
            },
            {
              "id": "761",
              "name": "Tropemedisin"
            },
            {
              "id": "762",
              "name": "Onkologi"
            },
            {
              "id": "763",
              "name": "Radiologi og bildediagnostikk"
            },
            {
              "id": "764",
              "name": "Fysikalsk medisin og rehabilitering"
            },
            {
              "id": "765",
              "name": "Anestesiologi"
            },
            {
              "id": "770",
              "name": "Generellindremedisin"
            },
            {
              "id": "771",
              "name": "Kardiologi"
            },
            {
              "id": "772",
              "name": "Nefrologi, urologi"
            },
            {
              "id": "773",
              "name": "Gasteroenterologi"
            },
            {
              "id": "774",
              "name": "Endokrinologi"
            },
            {
              "id": "775",
              "name": "Hematologi"
            },
            {
              "id": "776",
              "name": "Infeksjonsmedisin"
            },
            {
              "id": "777",
              "name": "Lungesykdommer"
            },
            {
              "id": "778",
              "name": "Geriatri"
            },
            {
              "id": "780",
              "name": "Generell kirurgi"
            },
            {
              "id": "781",
              "name": "Gasteroenterologisk kirurgi"
            },
            {
              "id": "782",
              "name": "Kar- og thoraxkirurgi"
            },
            {
              "id": "783",
              "name": "Traumatologi"
            },
            {
              "id": "784",
              "name": "Ortopedisk kirurgi"
            },
            {
              "id": "785",
              "name": "Plastisk kirurgi"
            },
            {
              "id": "786",
              "name": "Nevrokirurgi"
            },
            {
              "id": "787",
              "name": "Kjevekirurgi"
            },
            {
              "id": "788",
              "name": "Endokrin kirurgi"
            },
            {
              "id": "799",
              "name": "Andre klinisk medisinske fag"
            }
          ]
        },
        {
          "id": "800",
          "name": "Helsefag",
          "subterms": [
            {
              "id": "801",
              "name": "Samfunnsmedisin, sosialmedisin"
            },
            {
              "id": "802",
              "name": "Samfunnsodontologi"
            },
            {
              "id": "803",
              "name": "Epidemiologi medisinsk og odontologisk statistikk"
            },
            {
              "id": "804",
              "name": "Forebyggende medisin"
            },
            {
              "id": "805",
              "name": "Medisinsk/odontologisketikk, atferdsfag, historie"
            },
            {
              "id": "806",
              "name": "Helsetjeneste- og helseadministrasjonsforskning"
            },
            {
              "id": "807",
              "name": "Fysioterapi"
            },
            {
              "id": "808",
              "name": "Sykepleievitenskap"
            },
            {
              "id": "809",
              "name": "Yrkesmedisin"
            },
            {
              "id": "810",
              "name": "Bedriftsmedisin"
            },
            {
              "id": "811",
              "name": "Ernæring"
            },
            {
              "id": "812",
              "name": "Samfunnsfarmasi"
            },
            {
              "id": "813",
              "name": "Næringsmiddelhygiene"
            },
            {
              "id": "829",
              "name": "Andre helsefag"
            }
          ]
        },
        {
          "id": "830",
          "name": "Klinisk odontologiske fag",
          "subterms": [
            {
              "id": "831",
              "name": "Konserverende tannpleie"
            },
            {
              "id": "832",
              "name": "Protetikk og bitt funksjon"
            },
            {
              "id": "833",
              "name": "Kjeveortopedi"
            },
            {
              "id": "834",
              "name": "Barnetannpleie og kariesprofylakse"
            },
            {
              "id": "835",
              "name": "Oral kirurgi"
            },
            {
              "id": "835",
              "name": "Oral medisin"
            },
            {
              "id": "836",
              "name": "Oral radiologi"
            },
            {
              "id": "837",
              "name": "Periodonti"
            },
            {
              "id": "849",
              "name": "Andre kliniske odontologiske fag"
            }
          ]
        },
        {
          "id": "850",
          "name": "Idrettsmedisinskefag",
          "subterms": [
            {
              "id": "851",
              "name": "Treningslære"
            },
            {
              "id": "852",
              "name": "Bevegelseslære"
            },
            {
              "id": "853",
              "name": "Doping/idrettsfarmakologi"
            }
          ]
        }
      ]
    },
    {
      "id": "900",
      "name": "Landbruks- og Fiskerifag",
      "subterms": [
        {
          "id": "910",
          "name": "Landbruksfag",
          "subterms": [
            {
              "id": "911",
              "name": "Planteforedling, hagebruk, plantevern, plantepatologi"
            },
            {
              "id": "912",
              "name": "Husdyravl, oppdrett, forplantning"
            },
            {
              "id": "913",
              "name": "Jordfag"
            },
            {
              "id": "914",
              "name": "Naturressursforvaltning"
            },
            {
              "id": "915",
              "name": "Skogbruk"
            },
            {
              "id": "916",
              "name": "Landbruksteknologi"
            },
            {
              "id": "918",
              "name": "Fôring"
            },
            {
              "id": "919",
              "name": "Andrelandbruksfag"
            }
          ]
        },
        {
          "id": "920",
          "name": "Fiskerifag",
          "subterms": [
            {
              "id": "921",
              "name": "Ressursbiologi"
            },
            {
              "id": "922",
              "name": "Akvakultur"
            },
            {
              "id": "923",
              "name": "Fiskehelse"
            },
            {
              "id": "924",
              "name": "Fiskeriteknologi"
            },
            {
              "id": "925",
              "name": "Fangst"
            },
            {
              "id": "929",
              "name": "Andre fiskerifag"
            }
          ]
        },
        {
          "id": "950",
          "name": "Klinisk veterinærmedisinske fag",
          "subterms": [
            {
              "id": "951",
              "name": "Reproduksjon"
            },
            {
              "id": "952",
              "name": "Obstetrikk"
            },
            {
              "id": "953",
              "name": "Kirurgi"
            },
            {
              "id": "954",
              "name": "Indremedisin"
            }
          ]
        }
      ]
    }
  ]
}
